inia/__init__.py
inia/client.py
inia/rackspace.py
inia/cloudformation/__init__.py
inia/cloudformation/client.py
inia/codesuite/__init__.py
inia/codesuite/client.py
inia/controltower/__init__.py
inia/controltower/client.py
inia/costexplorer/__init__.py
inia/costexplorer/client.py
inia/servicecatalog/__init__.py
inia/servicecatalog/client.py
inia/singlesignon/__init__.py
inia/singlesignon/client.py
inia/stepfunctions/__init__.py
inia/stepfunctions/client.py
inia-1.1.0.dist-info/METADATA
inia-1.1.0.dist-info/WHEEL
inia-1.1.0.dist-info/top_level.txt
inia-1.1.0.dist-info/RECORD
