Metadata-Version: 2.4
Name: inia
Version: 1.1.0
Summary: Inia extends boto3 by adding missing functions and providing convenient wrappers for existing boto3 operations.
Home-page: https://github.com/grnet/inia
Author: GRNET DevOps Team
Author-email: devops-rnd@grnet.gr
License: MIT
Requires-Dist: boto3==1.38.5
Requires-Dist: botocore==1.38.5
Requires-Dist: requests==2.32.4
Requires-Dist: requests-aws4auth==1.3.1
Dynamic: author
Dynamic: author-email
Dynamic: description
Dynamic: description-content-type
Dynamic: home-page
Dynamic: license
Dynamic: requires-dist
Dynamic: summary
